core/__init__.py
core/color_pixels.py
cv/__init__.py
cv/image.py
io_util/__init__.py
io_util/image.py
LinearRecolor-1.0.0.dist-info/METADATA
LinearRecolor-1.0.0.dist-info/WHEEL
LinearRecolor-1.0.0.dist-info/top_level.txt
LinearRecolor-1.0.0.dist-info/RECORD
